ghicon
