Metadata-Version: 2.1
Name: ghicon
Version: 5.2.0
Summary: GitHubesque identicon generator.
Home-page: https://github.com/agzg/ghicon
Author: Ali Azam
Author-email: azam.vw@gmail.com
License: MIT
Download-URL: https://github.com/agzg/ghicon/archive/refs/tags/5.2.0.tar.gz
Keywords: identicon,generator,github,pillow,icon
Platform: UNKNOWN
Classifier: License :: OSI Approved :: MIT License
Classifier: Programming Language :: Python :: 3.8
Classifier: Programming Language :: Python :: 3.9
Classifier: Programming Language :: Python :: 3.10
License-File: LICENSE
